Workbook
Name Aporte: Case_dividendos!$D$16
Name dividendos_mensal: Case_dividendos!$D$20
Name patrimonio_acumulado: Case_dividendos!$D$19
Name qtd_ano: Case_dividendos!$D$17
Name rendimento_carteira: Case_dividendos!$D$12
Name Salario: Case_dividendos!$D$11
Name sugestao_investimento: Case_dividendos!$D$13
Name taxa_mensal: Case_dividendos!$D$18

Sheet Case_dividendos
B10: Configurações
B11: Salário | D11: 3200
B12: Rendimento Carteira | D12: 0.01
B13: Sugestão de Investimento | D13: =D11*30% -> 960
B15: INVESTIMENTO MENSAL
B16: Quanto devo investir por mês? | D16: 650
B17: por quantos anos ? | D17: 5
B18: Taxa de rendimento mensal ? | D18: 0.01
B19: Quanto de patrimônio acumulado? | D19: =FV(D18,D17*12,D16*-1) -> 53085.285
B20: Quanto é os dividentos mensais? | D20: =D19*$D$12 -> 530.85285
B22: Cenários | D22: Dividendos
A23: 2 | B23: Quanto em 2 Anos? | C23: =FV($D$18,$A23*12,$D$16*-1) -> 17532.752 | D23: =C23*$D$12 -> 175.32752
A24: 5 | B24: Quanto em 5 Anos? | C24: =FV($D$18,$A24*12,$D$16*-1) -> 53085.285 | D24: =C24*$D$12 -> 530.85285
A25: 10 | B25: Quanto em 10 Anos? | C25: =FV($D$18,$A25*12,$D$16*-1) -> 149525.15 | D25: =C25*$D$12 -> 1495.2515
A26: 20 | B26: Quanto em 20 Anos? | C26: =FV($D$18,$A26*12,$D$16*-1) -> 643015.99 | D26: =C26*$D$12 -> 6430.1599
A27: 30 | B27: Quanto em 30 Anos? | C27: =FV($D$18,$A27*12,$D$16*-1) -> 2271726.7 | D27: =C27*$D$12 -> 22717.267
B31: Perfil | C31: AGRESSIVO
B32: VALOR A SER INVESTIDO POR MÊS | C32: =D13 -> 960
B35: TIPO DE FII | C35: PERCENTUAL SUGERIDO | D35: VALORES
B36: PAPEL | C36: =VLOOKUP($C$31&"-"&B36,Planilha1!$A:$D,4,FALSE) -> 0.5 | D36: =$C$32*C36 -> 480
B37: TIJOLO | C37: =VLOOKUP($C$31&"-"&B37,Planilha1!$A:$D,4,FALSE) -> 0.1 | D37: =$C$32*C37 -> 96
B38: HÍBRIDOS | C38: =VLOOKUP($C$31&"-"&B38,Planilha1!$A:$D,4,FALSE) -> 0.05 | D38: =$C$32*C38 -> 48
B39: FOFs | C39: =VLOOKUP($C$31&"-"&B39,Planilha1!$A:$D,4,FALSE) -> 0.05 | D39: =$C$32*C39 -> 48
B40: DESENVOLMVIMENTO | C40: =VLOOKUP($C$31&"-"&B40,Planilha1!$A:$D,4,FALSE) -> 0.2 | D40: =$C$32*C40 -> 192
B41: HOTELARIAS | C41: =VLOOKUP($C$31&"-"&B41,Planilha1!$A:$D,4,FALSE) -> 0.1 | D41: =$C$32*C41 -> 96
D42: =SUM(D36:D41) -> 960

Sheet Planilha1
A3: CHAVE | B3: PERFIL | C3: TIPO DE FII | D3: %
A4: =$B$4&"-"&C4 -> CONSERVADOR-PAPEL | B4: CONSERVADOR | C4: PAPEL | D4: 0.3
A5: =$B$4&"-"&C5 -> CONSERVADOR-TIJOLO | B5: CONSERVADOR | C5: TIJOLO | D5: 0.5 | J5: %
A6: =$B$4&"-"&C6 -> CONSERVADOR-HÍBRIDOS | B6: CONSERVADOR | C6: HÍBRIDOS | D6: 0.1 | I6: MODERADO-TIJOLO | J6: =VLOOKUP(I6,$A$3:$D$21,4,) -> 0.4
A7: =$B$4&"-"&C7 -> CONSERVADOR-FOFs | B7: CONSERVADOR | C7: FOFs | D7: 0.1
A8: =$B$4&"-"&C8 -> CONSERVADOR-DESENVOLMVIMENTO | B8: CONSERVADOR | C8: DESENVOLMVIMENTO | D8: 0
A9: =$B$4&"-"&C9 -> CONSERVADOR-HOTELARIAS | B9: CONSERVADOR | C9: HOTELARIAS | D9: 0
A10: =$B$10&"-"&C10 -> MODERADO-PAPEL | B10: MODERADO | C10: PAPEL | D10: 0.32
A11: =$B$10&"-"&C11 -> MODERADO-TIJOLO | B11: MODERADO | C11: TIJOLO | D11: 0.4
A12: =$B$10&"-"&C12 -> MODERADO-HÍBRIDOS | B12: MODERADO | C12: HÍBRIDOS | D12: 0.08
A13: =$B$10&"-"&C13 -> MODERADO-FOFs | B13: MODERADO | C13: FOFs | D13: 0.1
A14: =$B$10&"-"&C14 -> MODERADO-DESENVOLMVIMENTO | B14: MODERADO | C14: DESENVOLMVIMENTO | D14: 0.1
A15: =$B$10&"-"&C15 -> MODERADO-HOTELARIAS | B15: MODERADO | C15: HOTELARIAS | D15: 0
A16: =$B$16&"-"&C16 -> AGRESSIVO-PAPEL | B16: AGRESSIVO | C16: PAPEL | D16: 0.5
A17: =$B$16&"-"&C17 -> AGRESSIVO-TIJOLO | B17: AGRESSIVO | C17: TIJOLO | D17: 0.1
A18: =$B$16&"-"&C18 -> AGRESSIVO-HÍBRIDOS | B18: AGRESSIVO | C18: HÍBRIDOS | D18: 0.05
A19: =$B$16&"-"&C19 -> AGRESSIVO-FOFs | B19: AGRESSIVO | C19: FOFs | D19: 0.05
A20: =$B$16&"-"&C20 -> AGRESSIVO-DESENVOLMVIMENTO | B20: AGRESSIVO | C20: DESENVOLMVIMENTO | D20: 0.2
A21: =$B$16&"-"&C21 -> AGRESSIVO-HOTELARIAS | B21: AGRESSIVO | C21: HOTELARIAS | D21: 0.1
